wordler/__init__.py
wordler/main.py
wordler/cli/__init__.py
wordler/cli/functions.py
wordler/data/words_and_counts.csv
wordler/solver/__init__.py
wordler/solver/_solver.py
wordler/tables/__init__.py
wordler/tables/_probability_tables.py
wordler_cli-0.0.1.dist-info/LICENSE
wordler_cli-0.0.1.dist-info/METADATA
wordler_cli-0.0.1.dist-info/WHEEL
wordler_cli-0.0.1.dist-info/entry_points.txt
wordler_cli-0.0.1.dist-info/top_level.txt
wordler_cli-0.0.1.dist-info/RECORD
