Metadata-Version: 2.1
Name: wordler-cli
Version: 0.0.1
Summary: Wordle solver!
Author: Kevin Schattin
License: MIT License
Project-URL: Homepage, https://github.com/k-bartolomeo/wordler
Project-URL: Issues, https://github.com/k-bartolomeo/wordler/issues
Classifier: Programming Language :: Python :: 3
Classifier: Programming Language :: Python
Classifier: Topic :: Software Development :: Libraries :: Python Modules
Classifier: Topic :: Software Development :: Libraries
Classifier: Topic :: Software Development
Classifier: Development Status :: 4 - Beta
Classifier: Programming Language :: Python :: 3 :: Only
Classifier: Programming Language :: Python :: 3.7
Classifier: Programming Language :: Python :: 3.8
Classifier: Programming Language :: Python :: 3.9
Classifier: Programming Language :: Python :: 3.10
Classifier: Programming Language :: Python :: 3.11
Classifier: Programming Language :: Python :: 3.12
Classifier: License :: OSI Approved :: MIT License
Requires-Python: >=3.9
License-File: LICENSE
Requires-Dist: questionary >=2.0.1
Requires-Dist: pandas >=2.2.2
Requires-Dist: numpy >=1.24.2
Requires-Dist: typer >=0.12.4
